markination/__init__.py
markination/ButtonPaginator.py
markination/DropdownPaginator.py
markination-0.2.3.dist-info/METADATA
markination-0.2.3.dist-info/WHEEL
markination-0.2.3.dist-info/RECORD
